LICENSE
README.md
setup.py
spillover_effects/__init__.py
spillover_effects/bounds.py
spillover_effects/bounds_ml.py
spillover_effects/utils.py
spillover_effects/wls.py
spillover_effects.egg-info/PKG-INFO
spillover_effects.egg-info/SOURCES.txt
spillover_effects.egg-info/dependency_links.txt
spillover_effects.egg-info/requires.txt
spillover_effects.egg-info/top_level.txt