Metadata-Version: 2.1
Name: spillover-effects
Version: 0.4.0
Summary: Estimate spillover effects of social network on a randomized experiment
Home-page: https://github.com/pabloestradac/spillover-effects
Author: Pablo Estrada
Author-email: pabloestradace@gmail.com
License: UNKNOWN
Platform: UNKNOWN
License-File: LICENSE
